goat_wallets/crossmint/__init__.py
goat_wallets/crossmint/api_client.py
goat_wallets/crossmint/base.py
goat_wallets/crossmint/base_wallet.py
goat_wallets/crossmint/chains.py
goat_wallets/crossmint/custodial_solana_wallet.py
goat_wallets/crossmint/evm_smart_wallet.py
goat_wallets/crossmint/faucet.py
goat_wallets/crossmint/faucet_plugin.py
goat_wallets/crossmint/mint.py
goat_wallets/crossmint/mint_plugin.py
goat_wallets/crossmint/parameters.py
goat_wallets/crossmint/service.py
goat_wallets/crossmint/solana_smart_wallet.py
goat_wallets/crossmint/solana_smart_wallet_factory.py
goat_wallets/crossmint/types.py
goat_wallets/crossmint/wallet.py
goat_wallets/crossmint/wallet_plugin.py
goat_sdk_wallet_crossmint-0.1.14.dist-info/METADATA
goat_sdk_wallet_crossmint-0.1.14.dist-info/WHEEL
goat_sdk_wallet_crossmint-0.1.14.dist-info/RECORD
