Metadata-Version: 2.1
Name: goat-sdk-wallet-crossmint
Version: 0.1.14
Summary: Crossmint wallet implementation for GOAT SDK
Home-page: https://ohmygoat.dev/
Keywords: goat,sdk,web3,agents,ai,crossmint,wallet
Author: GOAT SDK Team
Requires-Python: >=3.10,<4.0
Classifier: Programming Language :: Python :: 3
Classifier: Programming Language :: Python :: 3.10
Classifier: Programming Language :: Python :: 3.11
Classifier: Programming Language :: Python :: 3.12
Requires-Dist: base58 (>=2.1)
Requires-Dist: eth-account (>=0.8)
Requires-Dist: goat-sdk (>=0.1.0,<0.2.0)
Requires-Dist: goat-sdk-wallet-evm (>=0.1.0,<0.2.0)
Requires-Dist: goat-sdk-wallet-solana (>=0.1.0,<0.2.0)
Requires-Dist: setuptools (>=70)
Requires-Dist: web3 (>=6.0.0)
Project-URL: Bug Tracker, https://github.com/goat-sdk/goat/issues
Project-URL: Repository, https://github.com/goat-sdk/goat
